{
  "$schema": "https://developer.microsoft.com/json-schemas/fabric/item/report/definition/visualContainer/2.4.0/schema.json",
  "name": "a426debaa000033aaeb0",
  "position": {
    "x": 15.623913946411466,
    "y": 171.86305341052613,
    "z": 4000,
    "height": 71.870004153492744,
    "width": 630.16452917192919,
    "tabOrder": 4000
  },
  "visualGroup": {
    "displayName": "Group 1",
    "groupMode": "ScaleMode",
    "objects": {
      "background": [
        {
          "properties": {
            "show": {
              "expr": {
                "Literal": {
                  "Value": "true"
                }
              }
            },
            "color": {
              "solid": {
                "color": {
                  "expr": {
                    "ThemeDataColor": {
                      "ColorId": 0,
                      "Percent": 0
                    }
                  }
                }
              }
            }
          }
        }
      ]
    }
  }
}